Metadata-Version: 1.0
Name: yos-cube
Version: 0.0.1
Summary: YOS command line tool for repositories version control, publishing and updating code from remotely hosted repositories, and invoking YOS own build system and export functions, among other operations
Home-page: https://code.aliyun.com/yos/yos-cube
Author: YOS
Author-email: yangsw@mxchip.com
License: Apache License
